{"name":"Moldova","isoCode":"MD","lat":47,"lon":29,"geocoding":{},"distantMaxMiles":5,"states":{"Anenii Noi District":{"countryName":"Moldova","name":"Anenii Noi District","isoCode":"AN","lat":46.8795663,"lon":29.2312175,"geocoding":{},"distantMaxMiles":5,"cities":{"Anenii Noi":{"countryName":"Moldova","stateName":"Anenii Noi District","name":"Anenii Noi","lat":46.87839,"lon":29.23483,"geocoding":{},"distantMaxMiles":5},"Varniţa":{"countryName":"Moldova","stateName":"Anenii Noi District","name":"Varniţa","lat":46.86606,"lon":29.46636,"geocoding":{},"distantMaxMiles":5}}},"Basarabeasca District":{"countryName":"Moldova","name":"Basarabeasca District","isoCode":"BS","lat":46.423706,"lon":28.8935492,"geocoding":{},"distantMaxMiles":5,"cities":{"Basarabeasca":{"countryName":"Moldova","stateName":"Basarabeasca District","name":"Basarabeasca","lat":46.3317,"lon":28.96365,"geocoding":{},"distantMaxMiles":5}}},"Bender Municipality":{"countryName":"Moldova","name":"Bender Municipality","isoCode":"BD","lat":46.8227551,"lon":29.4620101,"geocoding":{},"distantMaxMiles":5,"cities":{"Bender":{"countryName":"Moldova","stateName":"Bender Municipality","name":"Bender","lat":46.83156,"lon":29.47769,"geocoding":{},"distantMaxMiles":5}}},"Briceni District":{"countryName":"Moldova","name":"Briceni District","isoCode":"BR","lat":48.3632022,"lon":27.0750398,"geocoding":{},"distantMaxMiles":5,"cities":{"Briceni":{"countryName":"Moldova","stateName":"Briceni District","name":"Briceni","lat":48.36289,"lon":27.07787,"geocoding":{},"distantMaxMiles":5}}},"Bălți Municipality":{"countryName":"Moldova","name":"Bălți Municipality","isoCode":"BA","lat":47.7539947,"lon":27.9184148,"geocoding":{},"distantMaxMiles":5,"cities":{"Bălţi":{"countryName":"Moldova","stateName":"Bălți Municipality","name":"Bălţi","lat":47.76314,"lon":27.92932,"geocoding":{},"distantMaxMiles":5}}},"Cahul District":{"countryName":"Moldova","name":"Cahul District","isoCode":"CA","lat":45.8939404,"lon":28.1890275,"geocoding":{},"distantMaxMiles":5,"cities":{"Cahul":{"countryName":"Moldova","stateName":"Cahul District","name":"Cahul","lat":45.90425,"lon":28.19929,"geocoding":{},"distantMaxMiles":5},"Giurgiuleşti":{"countryName":"Moldova","stateName":"Cahul District","name":"Giurgiuleşti","lat":45.48167,"lon":28.19722,"geocoding":{},"distantMaxMiles":5}}},"Cantemir District":{"countryName":"Moldova","name":"Cantemir District","isoCode":"CT","lat":46.2771742,"lon":28.2009653,"geocoding":{},"distantMaxMiles":5,"cities":{"Cantemir":{"countryName":"Moldova","stateName":"Cantemir District","name":"Cantemir","lat":46.27743,"lon":28.2027,"geocoding":{},"distantMaxMiles":5},"Iargara":{"countryName":"Moldova","stateName":"Cantemir District","name":"Iargara","lat":46.4252,"lon":28.42676,"geocoding":{},"distantMaxMiles":5},"Vişniovca":{"countryName":"Moldova","stateName":"Cantemir District","name":"Vişniovca","lat":46.3326,"lon":28.44797,"geocoding":{},"distantMaxMiles":5}}},"Chișinău Municipality":{"countryName":"Moldova","name":"Chișinău Municipality","isoCode":"CU","lat":47.0104529,"lon":28.8638102,"geocoding":{},"distantMaxMiles":5,"cities":{"Chisinau":{"countryName":"Moldova","stateName":"Chișinău Municipality","name":"Chisinau","lat":47.00556,"lon":28.8575,"geocoding":{},"distantMaxMiles":5},"Ciorescu":{"countryName":"Moldova","stateName":"Chișinău Municipality","name":"Ciorescu","lat":47.13,"lon":28.88937,"geocoding":{},"distantMaxMiles":5},"Cricova":{"countryName":"Moldova","stateName":"Chișinău Municipality","name":"Cricova","lat":47.13835,"lon":28.86156,"geocoding":{},"distantMaxMiles":5},"Stăuceni":{"countryName":"Moldova","stateName":"Chișinău Municipality","name":"Stăuceni","lat":47.09643,"lon":28.86791,"geocoding":{},"distantMaxMiles":5},"Sîngera":{"countryName":"Moldova","stateName":"Chișinău Municipality","name":"Sîngera","lat":46.91557,"lon":28.96673,"geocoding":{},"distantMaxMiles":5},"Vadul lui Vodă":{"countryName":"Moldova","stateName":"Chișinău Municipality","name":"Vadul lui Vodă","lat":47.09009,"lon":29.0757,"geocoding":{},"distantMaxMiles":5},"Vatra":{"countryName":"Moldova","stateName":"Chișinău Municipality","name":"Vatra","lat":47.0746,"lon":28.73685,"geocoding":{},"distantMaxMiles":5}}},"Cimișlia District":{"countryName":"Moldova","name":"Cimișlia District","isoCode":"CM","lat":46.5250851,"lon":28.7721835,"geocoding":{},"distantMaxMiles":5,"cities":{"Cimişlia":{"countryName":"Moldova","stateName":"Cimișlia District","name":"Cimişlia","lat":46.52685,"lon":28.76441,"geocoding":{},"distantMaxMiles":5}}},"Criuleni District":{"countryName":"Moldova","name":"Criuleni District","isoCode":"CR","lat":47.2136114,"lon":29.1557519,"geocoding":{},"distantMaxMiles":5,"cities":{"Criuleni":{"countryName":"Moldova","stateName":"Criuleni District","name":"Criuleni","lat":47.21307,"lon":29.15926,"geocoding":{},"distantMaxMiles":5}}},"Călărași District":{"countryName":"Moldova","name":"Călărași District","isoCode":"CL","lat":47.286946,"lon":28.274531,"geocoding":{},"distantMaxMiles":5,"cities":{"Călăraşi":{"countryName":"Moldova","stateName":"Călărași District","name":"Călăraşi","lat":47.2556,"lon":28.30987,"geocoding":{},"distantMaxMiles":5}}},"Căușeni District":{"countryName":"Moldova","name":"Căușeni District","isoCode":"CS","lat":46.6554715,"lon":29.4091222,"geocoding":{},"distantMaxMiles":5,"cities":{"Chiţcani":{"countryName":"Moldova","stateName":"Căușeni District","name":"Chiţcani","lat":46.78296,"lon":29.61682,"geocoding":{},"distantMaxMiles":5},"Căuşeni":{"countryName":"Moldova","stateName":"Căușeni District","name":"Căuşeni","lat":46.63674,"lon":29.41114,"geocoding":{},"distantMaxMiles":5}}},"Dondușeni District":{"countryName":"Moldova","name":"Dondușeni District","isoCode":"DO","lat":48.2338305,"lon":27.5998087,"geocoding":{},"distantMaxMiles":5,"cities":{"Briceni":{"countryName":"Moldova","stateName":"Dondușeni District","name":"Briceni","lat":48.35628,"lon":27.70293,"geocoding":{},"distantMaxMiles":5},"Donduşeni":{"countryName":"Moldova","stateName":"Dondușeni District","name":"Donduşeni","lat":48.24268,"lon":27.6101,"geocoding":{},"distantMaxMiles":5}}},"Drochia District":{"countryName":"Moldova","name":"Drochia District","isoCode":"DR","lat":48.0797788,"lon":27.8604114,"geocoding":{},"distantMaxMiles":5,"cities":{"Drochia":{"countryName":"Moldova","stateName":"Drochia District","name":"Drochia","lat":48.03555,"lon":27.81293,"geocoding":{},"distantMaxMiles":5}}},"Dubăsari District":{"countryName":"Moldova","name":"Dubăsari District","isoCode":"DU","lat":47.2643942,"lon":29.1550348,"geocoding":{},"distantMaxMiles":5,"cities":{"Cocieri":{"countryName":"Moldova","stateName":"Dubăsari District","name":"Cocieri","lat":47.3017,"lon":29.11755,"geocoding":{},"distantMaxMiles":5},"Ustia":{"countryName":"Moldova","stateName":"Dubăsari District","name":"Ustia","lat":47.25524,"lon":29.12406,"geocoding":{},"distantMaxMiles":5}}},"Edineț District":{"countryName":"Moldova","name":"Edineț District","isoCode":"ED","lat":48.1678991,"lon":27.2936143,"geocoding":{},"distantMaxMiles":5,"cities":{"Edineţ":{"countryName":"Moldova","stateName":"Edineț District","name":"Edineţ","lat":48.17215,"lon":27.30337,"geocoding":{},"distantMaxMiles":5}}},"Florești District":{"countryName":"Moldova","name":"Florești District","isoCode":"FL","lat":47.8667849,"lon":28.3391864,"geocoding":{},"distantMaxMiles":5,"cities":{"Floreşti":{"countryName":"Moldova","stateName":"Florești District","name":"Floreşti","lat":47.89137,"lon":28.29312,"geocoding":{},"distantMaxMiles":5},"Ghindești":{"countryName":"Moldova","stateName":"Florești District","name":"Ghindești","lat":47.85482,"lon":28.37679,"geocoding":{},"distantMaxMiles":5},"Mărculeşti":{"countryName":"Moldova","stateName":"Florești District","name":"Mărculeşti","lat":47.86897,"lon":28.24109,"geocoding":{},"distantMaxMiles":5}}},"Fălești District":{"countryName":"Moldova","name":"Fălești District","isoCode":"FA","lat":47.5647725,"lon":27.7265593,"geocoding":{},"distantMaxMiles":5,"cities":{"Fălești":{"countryName":"Moldova","stateName":"Fălești District","name":"Fălești","lat":47.57667,"lon":27.71264,"geocoding":{},"distantMaxMiles":5}}},"Gagauzia":{"countryName":"Moldova","name":"Gagauzia","isoCode":"GA","lat":46.0979435,"lon":28.6384645,"geocoding":{},"distantMaxMiles":5,"cities":{"Bugeac":{"countryName":"Moldova","stateName":"Gagauzia","name":"Bugeac","lat":46.36554,"lon":28.6625,"geocoding":{},"distantMaxMiles":5},"Ceadîr-Lunga":{"countryName":"Moldova","stateName":"Gagauzia","name":"Ceadîr-Lunga","lat":46.06169,"lon":28.83078,"geocoding":{},"distantMaxMiles":5},"Comrat":{"countryName":"Moldova","stateName":"Gagauzia","name":"Comrat","lat":46.29456,"lon":28.6565,"geocoding":{},"distantMaxMiles":5},"Vulcăneşti":{"countryName":"Moldova","stateName":"Gagauzia","name":"Vulcăneşti","lat":45.68492,"lon":28.40613,"geocoding":{},"distantMaxMiles":5}}},"Glodeni District":{"countryName":"Moldova","name":"Glodeni District","isoCode":"GL","lat":47.7790156,"lon":27.516801,"geocoding":{},"distantMaxMiles":5,"cities":{"Glodeni":{"countryName":"Moldova","stateName":"Glodeni District","name":"Glodeni","lat":47.77513,"lon":27.51891,"geocoding":{},"distantMaxMiles":5}}},"Hîncești District":{"countryName":"Moldova","name":"Hîncești District","isoCode":"HI","lat":46.8281147,"lon":28.5850889,"geocoding":{},"distantMaxMiles":5,"cities":{"Dancu":{"countryName":"Moldova","stateName":"Hîncești District","name":"Dancu","lat":46.75818,"lon":28.20716,"geocoding":{},"distantMaxMiles":5},"Hînceşti":{"countryName":"Moldova","stateName":"Hîncești District","name":"Hînceşti","lat":46.83047,"lon":28.59064,"geocoding":{},"distantMaxMiles":5}}},"Ialoveni District":{"countryName":"Moldova","name":"Ialoveni District","isoCode":"IA","lat":46.863086,"lon":28.8234218,"geocoding":{},"distantMaxMiles":5,"cities":{"Ialoveni":{"countryName":"Moldova","stateName":"Ialoveni District","name":"Ialoveni","lat":46.94346,"lon":28.78233,"geocoding":{},"distantMaxMiles":5}}},"Nisporeni District":{"countryName":"Moldova","name":"Nisporeni District","isoCode":"NI","lat":47.0751349,"lon":28.1768155,"geocoding":{},"distantMaxMiles":5,"cities":{"Nisporeni":{"countryName":"Moldova","stateName":"Nisporeni District","name":"Nisporeni","lat":47.08159,"lon":28.17138,"geocoding":{},"distantMaxMiles":5}}},"Ocnița District":{"countryName":"Moldova","name":"Ocnița District","isoCode":"OC","lat":48.4110435,"lon":27.4768092,"geocoding":{},"distantMaxMiles":5,"cities":{"Ocniţa":{"countryName":"Moldova","stateName":"Ocnița District","name":"Ocniţa","lat":48.38274,"lon":27.43805,"geocoding":{},"distantMaxMiles":5},"Otaci":{"countryName":"Moldova","stateName":"Ocnița District","name":"Otaci","lat":48.43285,"lon":27.79912,"geocoding":{},"distantMaxMiles":5}}},"Orhei District":{"countryName":"Moldova","name":"Orhei District","isoCode":"OR","lat":47.38604,"lon":28.8303082,"geocoding":{},"distantMaxMiles":5,"cities":{"Orhei":{"countryName":"Moldova","stateName":"Orhei District","name":"Orhei","lat":47.38494,"lon":28.82446,"geocoding":{},"distantMaxMiles":5}}},"Rezina District":{"countryName":"Moldova","name":"Rezina District","isoCode":"RE","lat":47.7180447,"lon":28.8871024,"geocoding":{},"distantMaxMiles":5,"cities":{"Rezina":{"countryName":"Moldova","stateName":"Rezina District","name":"Rezina","lat":47.74928,"lon":28.96583,"geocoding":{},"distantMaxMiles":5},"Saharna":{"countryName":"Moldova","stateName":"Rezina District","name":"Saharna","lat":47.69107,"lon":28.97458,"geocoding":{},"distantMaxMiles":5}}},"Rîșcani District":{"countryName":"Moldova","name":"Rîșcani District","isoCode":"RI","lat":47.9070153,"lon":27.5374996,"geocoding":{},"distantMaxMiles":5,"cities":{"Rîşcani":{"countryName":"Moldova","stateName":"Rîșcani District","name":"Rîşcani","lat":47.94792,"lon":27.56376,"geocoding":{},"distantMaxMiles":5}}},"Soroca District":{"countryName":"Moldova","name":"Soroca District","isoCode":"SO","lat":48.1549743,"lon":28.2870783,"geocoding":{},"distantMaxMiles":5,"cities":{"Soroca":{"countryName":"Moldova","stateName":"Soroca District","name":"Soroca","lat":48.15659,"lon":28.28489,"geocoding":{},"distantMaxMiles":5}}},"Strășeni District":{"countryName":"Moldova","name":"Strășeni District","isoCode":"ST","lat":47.1450267,"lon":28.6136736,"geocoding":{},"distantMaxMiles":5,"cities":{"Bucovăţ":{"countryName":"Moldova","stateName":"Strășeni District","name":"Bucovăţ","lat":47.19064,"lon":28.45802,"geocoding":{},"distantMaxMiles":5},"Strășeni":{"countryName":"Moldova","stateName":"Strășeni District","name":"Strășeni","lat":47.14216,"lon":28.60774,"geocoding":{},"distantMaxMiles":5}}},"Sîngerei District":{"countryName":"Moldova","name":"Sîngerei District","isoCode":"SI","lat":47.6389134,"lon":28.1371816,"geocoding":{},"distantMaxMiles":5,"cities":{"Bilicenii Vechi":{"countryName":"Moldova","stateName":"Sîngerei District","name":"Bilicenii Vechi","lat":47.6558,"lon":28.04734,"geocoding":{},"distantMaxMiles":5},"Biruinţa":{"countryName":"Moldova","stateName":"Sîngerei District","name":"Biruinţa","lat":47.81353,"lon":28.07004,"geocoding":{},"distantMaxMiles":5},"Sîngerei":{"countryName":"Moldova","stateName":"Sîngerei District","name":"Sîngerei","lat":47.63632,"lon":28.14296,"geocoding":{},"distantMaxMiles":5}}},"Taraclia District":{"countryName":"Moldova","name":"Taraclia District","isoCode":"TA","lat":45.898651,"lon":28.6671644,"geocoding":{},"distantMaxMiles":5,"cities":{"Taraclia":{"countryName":"Moldova","stateName":"Taraclia District","name":"Taraclia","lat":45.90273,"lon":28.66816,"geocoding":{},"distantMaxMiles":5},"Tvardița":{"countryName":"Moldova","stateName":"Taraclia District","name":"Tvardița","lat":46.14826,"lon":28.96491,"geocoding":{},"distantMaxMiles":5}}},"Telenești District":{"countryName":"Moldova","name":"Telenești District","isoCode":"TE","lat":47.4983962,"lon":28.3676019,"geocoding":{},"distantMaxMiles":5,"cities":{"Mîndreşti":{"countryName":"Moldova","stateName":"Telenești District","name":"Mîndreşti","lat":47.50525,"lon":28.27687,"geocoding":{},"distantMaxMiles":5},"Teleneşti":{"countryName":"Moldova","stateName":"Telenești District","name":"Teleneşti","lat":47.5011,"lon":28.36536,"geocoding":{},"distantMaxMiles":5}}},"Transnistria autonomous territorial unit":{"countryName":"Moldova","name":"Transnistria autonomous territorial unit","isoCode":"SN","lat":47.2152972,"lon":29.4638054,"geocoding":{},"distantMaxMiles":5,"cities":{"Camenca":{"countryName":"Moldova","stateName":"Transnistria autonomous territorial unit","name":"Camenca","lat":48.03233,"lon":28.69899,"geocoding":{},"distantMaxMiles":5},"Crasnoe":{"countryName":"Moldova","stateName":"Transnistria autonomous territorial unit","name":"Crasnoe","lat":46.64844,"lon":29.80403,"geocoding":{},"distantMaxMiles":5},"Dnestrovsc":{"countryName":"Moldova","stateName":"Transnistria autonomous territorial unit","name":"Dnestrovsc","lat":46.6164,"lon":29.91926,"geocoding":{},"distantMaxMiles":5},"Dubăsari":{"countryName":"Moldova","stateName":"Transnistria autonomous territorial unit","name":"Dubăsari","lat":47.26562,"lon":29.16667,"geocoding":{},"distantMaxMiles":5},"Hryhoriopol":{"countryName":"Moldova","stateName":"Transnistria autonomous territorial unit","name":"Hryhoriopol","lat":47.15413,"lon":29.30008,"geocoding":{},"distantMaxMiles":5},"Maiac":{"countryName":"Moldova","stateName":"Transnistria autonomous territorial unit","name":"Maiac","lat":47.23727,"lon":29.38498,"geocoding":{},"distantMaxMiles":5},"Pervomaisc":{"countryName":"Moldova","stateName":"Transnistria autonomous territorial unit","name":"Pervomaisc","lat":46.73253,"lon":29.9617,"geocoding":{},"distantMaxMiles":5},"Rîbniţa":{"countryName":"Moldova","stateName":"Transnistria autonomous territorial unit","name":"Rîbniţa","lat":47.76817,"lon":29.01,"geocoding":{},"distantMaxMiles":5},"Slobozia":{"countryName":"Moldova","stateName":"Transnistria autonomous territorial unit","name":"Slobozia","lat":46.72927,"lon":29.70446,"geocoding":{},"distantMaxMiles":5},"Tiraspol":{"countryName":"Moldova","stateName":"Transnistria autonomous territorial unit","name":"Tiraspol","lat":46.84274,"lon":29.62909,"geocoding":{},"distantMaxMiles":5},"Tiraspolul Nou":{"countryName":"Moldova","stateName":"Transnistria autonomous territorial unit","name":"Tiraspolul Nou","lat":46.82874,"lon":29.52174,"geocoding":{},"distantMaxMiles":5}}},"Ungheni District":{"countryName":"Moldova","name":"Ungheni District","isoCode":"UN","lat":47.2305767,"lon":27.7892661,"geocoding":{},"distantMaxMiles":5,"cities":{"Ungheni":{"countryName":"Moldova","stateName":"Ungheni District","name":"Ungheni","lat":47.21079,"lon":27.80047,"geocoding":{},"distantMaxMiles":5}}},"Șoldănești District":{"countryName":"Moldova","name":"Șoldănești District","isoCode":"SD","lat":47.8147389,"lon":28.7889586,"geocoding":{},"distantMaxMiles":5,"cities":{"Şoldăneşti":{"countryName":"Moldova","stateName":"Șoldănești District","name":"Şoldăneşti","lat":47.81608,"lon":28.79718,"geocoding":{},"distantMaxMiles":5}}},"Ștefan Vodă District":{"countryName":"Moldova","name":"Ștefan Vodă District","isoCode":"SV","lat":46.5540488,"lon":29.702242,"geocoding":{},"distantMaxMiles":5,"cities":{"Ştefan Vodă":{"countryName":"Moldova","stateName":"Ștefan Vodă District","name":"Ştefan Vodă","lat":46.51287,"lon":29.66193,"geocoding":{},"distantMaxMiles":5}}}}}