{"name":"Tanzania","isoCode":"TZ","lat":-6,"lon":35,"geocoding":{},"distantMaxMiles":5,"states":{"Arusha":{"countryName":"Tanzania","name":"Arusha","isoCode":"01","lat":-3.3869254,"lon":36.6829927,"geocoding":{},"distantMaxMiles":5,"cities":{"Arusha":{"countryName":"Tanzania","stateName":"Arusha","name":"Arusha","lat":-3.36667,"lon":36.68333,"geocoding":{},"distantMaxMiles":5},"Kingori":{"countryName":"Tanzania","stateName":"Arusha","name":"Kingori","lat":-3.28333,"lon":36.98333,"geocoding":{},"distantMaxMiles":5},"Kiratu":{"countryName":"Tanzania","stateName":"Arusha","name":"Kiratu","lat":-3.33333,"lon":35.66667,"geocoding":{},"distantMaxMiles":5},"Longido":{"countryName":"Tanzania","stateName":"Arusha","name":"Longido","lat":-2.73319,"lon":36.69773,"geocoding":{},"distantMaxMiles":5},"Mbuguni":{"countryName":"Tanzania","stateName":"Arusha","name":"Mbuguni","lat":-3.56667,"lon":36.95,"geocoding":{},"distantMaxMiles":5},"Merelani":{"countryName":"Tanzania","stateName":"Arusha","name":"Merelani","lat":-3.56182,"lon":36.97895,"geocoding":{},"distantMaxMiles":5},"Meru":{"countryName":"Tanzania","stateName":"Arusha","name":"Meru","lat":-3.305,"lon":36.801,"geocoding":{},"distantMaxMiles":5},"Monduli":{"countryName":"Tanzania","stateName":"Arusha","name":"Monduli","lat":-3.3,"lon":36.45,"geocoding":{},"distantMaxMiles":5},"Mto wa Mbu":{"countryName":"Tanzania","stateName":"Arusha","name":"Mto wa Mbu","lat":-3.35,"lon":35.85,"geocoding":{},"distantMaxMiles":5},"Namanga":{"countryName":"Tanzania","stateName":"Arusha","name":"Namanga","lat":-2.55116,"lon":36.78377,"geocoding":{},"distantMaxMiles":5},"Ngorongoro":{"countryName":"Tanzania","stateName":"Arusha","name":"Ngorongoro","lat":-3.23973,"lon":35.48747,"geocoding":{},"distantMaxMiles":5},"Nkoaranga":{"countryName":"Tanzania","stateName":"Arusha","name":"Nkoaranga","lat":-3.33333,"lon":36.8,"geocoding":{},"distantMaxMiles":5},"Poli":{"countryName":"Tanzania","stateName":"Arusha","name":"Poli","lat":-3.33333,"lon":36.8,"geocoding":{},"distantMaxMiles":5},"Usa River":{"countryName":"Tanzania","stateName":"Arusha","name":"Usa River","lat":-3.36667,"lon":36.85,"geocoding":{},"distantMaxMiles":5}}},"Dar es Salaam":{"countryName":"Tanzania","name":"Dar es Salaam","isoCode":"02","lat":-6.792354,"lon":39.2083284,"geocoding":{},"distantMaxMiles":5,"cities":{"Dar es Salaam":{"countryName":"Tanzania","stateName":"Dar es Salaam","name":"Dar es Salaam","lat":-6.82349,"lon":39.26951,"geocoding":{},"distantMaxMiles":5},"Magomeni":{"countryName":"Tanzania","stateName":"Dar es Salaam","name":"Magomeni","lat":-6.8,"lon":39.25,"geocoding":{},"distantMaxMiles":5}}},"Dodoma":{"countryName":"Tanzania","name":"Dodoma","isoCode":"03","lat":-6.5738228,"lon":36.2630846,"geocoding":{},"distantMaxMiles":5,"cities":{"Dodoma":{"countryName":"Tanzania","stateName":"Dodoma","name":"Dodoma","lat":-6.17221,"lon":35.73947,"geocoding":{},"distantMaxMiles":5},"Kibakwe":{"countryName":"Tanzania","stateName":"Dodoma","name":"Kibakwe","lat":-6.71667,"lon":36.36667,"geocoding":{},"distantMaxMiles":5},"Kisasa":{"countryName":"Tanzania","stateName":"Dodoma","name":"Kisasa","lat":-6.17526,"lon":35.79266,"geocoding":{},"distantMaxMiles":5},"Kondoa":{"countryName":"Tanzania","stateName":"Dodoma","name":"Kondoa","lat":-4.70931,"lon":35.86227,"geocoding":{},"distantMaxMiles":5},"Kongwa":{"countryName":"Tanzania","stateName":"Dodoma","name":"Kongwa","lat":-6.2,"lon":36.41667,"geocoding":{},"distantMaxMiles":5},"Mpwapwa":{"countryName":"Tanzania","stateName":"Dodoma","name":"Mpwapwa","lat":-6.35,"lon":36.48333,"geocoding":{},"distantMaxMiles":5},"Msanga":{"countryName":"Tanzania","stateName":"Dodoma","name":"Msanga","lat":-6.05,"lon":36.03333,"geocoding":{},"distantMaxMiles":5}}},"Geita":{"countryName":"Tanzania","name":"Geita","isoCode":"27","lat":-2.8242257,"lon":32.2653887,"geocoding":{},"distantMaxMiles":5,"cities":{"Buseresere":{"countryName":"Tanzania","stateName":"Geita","name":"Buseresere","lat":-3.02361,"lon":31.87472,"geocoding":{},"distantMaxMiles":5},"Chato":{"countryName":"Tanzania","stateName":"Geita","name":"Chato","lat":-2.63778,"lon":31.76694,"geocoding":{},"distantMaxMiles":5},"Geita":{"countryName":"Tanzania","stateName":"Geita","name":"Geita","lat":-2.8725,"lon":32.2325,"geocoding":{},"distantMaxMiles":5},"Kasamwa":{"countryName":"Tanzania","stateName":"Geita","name":"Kasamwa","lat":-2.85,"lon":32.43333,"geocoding":{},"distantMaxMiles":5},"Katoro":{"countryName":"Tanzania","stateName":"Geita","name":"Katoro","lat":-3.02028,"lon":31.89583,"geocoding":{},"distantMaxMiles":5},"Masumbwe":{"countryName":"Tanzania","stateName":"Geita","name":"Masumbwe","lat":-3.63333,"lon":32.18333,"geocoding":{},"distantMaxMiles":5},"Ushirombo":{"countryName":"Tanzania","stateName":"Geita","name":"Ushirombo","lat":-3.49194,"lon":31.96389,"geocoding":{},"distantMaxMiles":5},"Uyovu":{"countryName":"Tanzania","stateName":"Geita","name":"Uyovu","lat":-3.28333,"lon":31.52583,"geocoding":{},"distantMaxMiles":5}}},"Iringa":{"countryName":"Tanzania","name":"Iringa","isoCode":"04","lat":-7.7887442,"lon":35.5657862,"geocoding":{},"distantMaxMiles":5,"cities":{"Ilula":{"countryName":"Tanzania","stateName":"Iringa","name":"Ilula","lat":-7.6766,"lon":36.03658,"geocoding":{},"distantMaxMiles":5},"Iringa":{"countryName":"Tanzania","stateName":"Iringa","name":"Iringa","lat":-7.76667,"lon":35.7,"geocoding":{},"distantMaxMiles":5},"Izazi":{"countryName":"Tanzania","stateName":"Iringa","name":"Izazi","lat":-7.2,"lon":35.73333,"geocoding":{},"distantMaxMiles":5},"Mafinga":{"countryName":"Tanzania","stateName":"Iringa","name":"Mafinga","lat":-7.25,"lon":35.06667,"geocoding":{},"distantMaxMiles":5},"Makungu":{"countryName":"Tanzania","stateName":"Iringa","name":"Makungu","lat":-8.73333,"lon":35.28333,"geocoding":{},"distantMaxMiles":5},"Malangali":{"countryName":"Tanzania","stateName":"Iringa","name":"Malangali","lat":-8.56667,"lon":34.85,"geocoding":{},"distantMaxMiles":5}}},"Kagera":{"countryName":"Tanzania","name":"Kagera","isoCode":"05","lat":-1.3001115,"lon":31.2626366,"geocoding":{},"distantMaxMiles":5,"cities":{"Biharamulo":{"countryName":"Tanzania","stateName":"Kagera","name":"Biharamulo","lat":-2.63194,"lon":31.30889,"geocoding":{},"distantMaxMiles":5},"Bugarama":{"countryName":"Tanzania","stateName":"Kagera","name":"Bugarama","lat":-2.87056,"lon":30.52806,"geocoding":{},"distantMaxMiles":5},"Bugene":{"countryName":"Tanzania","stateName":"Kagera","name":"Bugene","lat":-1.59111,"lon":31.14028,"geocoding":{},"distantMaxMiles":5},"Bukoba":{"countryName":"Tanzania","stateName":"Kagera","name":"Bukoba","lat":-1.33167,"lon":31.81222,"geocoding":{},"distantMaxMiles":5},"Kabanga":{"countryName":"Tanzania","stateName":"Kagera","name":"Kabanga","lat":-2.63861,"lon":30.46778,"geocoding":{},"distantMaxMiles":5},"Kamachumu":{"countryName":"Tanzania","stateName":"Kagera","name":"Kamachumu","lat":-1.61861,"lon":31.62,"geocoding":{},"distantMaxMiles":5},"Katerero":{"countryName":"Tanzania","stateName":"Kagera","name":"Katerero","lat":-1.4,"lon":31.73333,"geocoding":{},"distantMaxMiles":5},"Katoro":{"countryName":"Tanzania","stateName":"Kagera","name":"Katoro","lat":-1.39972,"lon":31.50028,"geocoding":{},"distantMaxMiles":5},"Kyaka":{"countryName":"Tanzania","stateName":"Kagera","name":"Kyaka","lat":-1.25222,"lon":31.42028,"geocoding":{},"distantMaxMiles":5},"Ngara":{"countryName":"Tanzania","stateName":"Kagera","name":"Ngara","lat":-2.51222,"lon":30.65583,"geocoding":{},"distantMaxMiles":5},"Nshamba":{"countryName":"Tanzania","stateName":"Kagera","name":"Nshamba","lat":-1.79833,"lon":31.55111,"geocoding":{},"distantMaxMiles":5},"Nsunga":{"countryName":"Tanzania","stateName":"Kagera","name":"Nsunga","lat":-1.14389,"lon":31.39472,"geocoding":{},"distantMaxMiles":5},"Nyakahanga":{"countryName":"Tanzania","stateName":"Kagera","name":"Nyakahanga","lat":-1.60333,"lon":31.14139,"geocoding":{},"distantMaxMiles":5},"Rulenge":{"countryName":"Tanzania","stateName":"Kagera","name":"Rulenge","lat":-2.7175,"lon":30.6325,"geocoding":{},"distantMaxMiles":5}}},"Katavi":{"countryName":"Tanzania","name":"Katavi","isoCode":"28","lat":-6.3677125,"lon":31.2626366,"geocoding":{},"distantMaxMiles":5,"cities":{"Inyonga":{"countryName":"Tanzania","stateName":"Katavi","name":"Inyonga","lat":-6.71667,"lon":32.06667,"geocoding":{},"distantMaxMiles":5},"Karema":{"countryName":"Tanzania","stateName":"Katavi","name":"Karema","lat":-6.82052,"lon":30.43887,"geocoding":{},"distantMaxMiles":5},"Mpanda":{"countryName":"Tanzania","stateName":"Katavi","name":"Mpanda","lat":-6.34379,"lon":31.06951,"geocoding":{},"distantMaxMiles":5},"Usevia":{"countryName":"Tanzania","stateName":"Katavi","name":"Usevia","lat":-7.1,"lon":31.23333,"geocoding":{},"distantMaxMiles":5}}},"Kigoma":{"countryName":"Tanzania","name":"Kigoma","isoCode":"08","lat":-4.8824092,"lon":29.6615055,"geocoding":{},"distantMaxMiles":5,"cities":{"Kakonko":{"countryName":"Tanzania","stateName":"Kigoma","name":"Kakonko","lat":-3.28278,"lon":30.96417,"geocoding":{},"distantMaxMiles":5},"Kasulu":{"countryName":"Tanzania","stateName":"Kigoma","name":"Kasulu","lat":-4.57667,"lon":30.1025,"geocoding":{},"distantMaxMiles":5},"Kibondo":{"countryName":"Tanzania","stateName":"Kigoma","name":"Kibondo","lat":-3.58639,"lon":30.72028,"geocoding":{},"distantMaxMiles":5},"Kigoma":{"countryName":"Tanzania","stateName":"Kigoma","name":"Kigoma","lat":-4.87694,"lon":29.62667,"geocoding":{},"distantMaxMiles":5},"Mabamba":{"countryName":"Tanzania","stateName":"Kigoma","name":"Mabamba","lat":-3.59833,"lon":30.50194,"geocoding":{},"distantMaxMiles":5},"Mwandiga":{"countryName":"Tanzania","stateName":"Kigoma","name":"Mwandiga","lat":-4.83,"lon":29.65806,"geocoding":{},"distantMaxMiles":5},"Nguruka":{"countryName":"Tanzania","stateName":"Kigoma","name":"Nguruka","lat":-5.10917,"lon":31.04194,"geocoding":{},"distantMaxMiles":5},"Uvinza":{"countryName":"Tanzania","stateName":"Kigoma","name":"Uvinza","lat":-5.10361,"lon":30.39111,"geocoding":{},"distantMaxMiles":5}}},"Kilimanjaro":{"countryName":"Tanzania","name":"Kilimanjaro","isoCode":"09","lat":-4.1336927,"lon":37.8087693,"geocoding":{},"distantMaxMiles":5,"cities":{"Hedaru":{"countryName":"Tanzania","stateName":"Kilimanjaro","name":"Hedaru","lat":-4.5,"lon":37.9,"geocoding":{},"distantMaxMiles":5},"Kihurio":{"countryName":"Tanzania","stateName":"Kilimanjaro","name":"Kihurio","lat":-4.46667,"lon":38.06667,"geocoding":{},"distantMaxMiles":5},"Kisiwani":{"countryName":"Tanzania","stateName":"Kilimanjaro","name":"Kisiwani","lat":-4.13333,"lon":37.95,"geocoding":{},"distantMaxMiles":5},"Kwakoa":{"countryName":"Tanzania","stateName":"Kilimanjaro","name":"Kwakoa","lat":-3.76667,"lon":37.71667,"geocoding":{},"distantMaxMiles":5},"Lembeni":{"countryName":"Tanzania","stateName":"Kilimanjaro","name":"Lembeni","lat":-3.78333,"lon":37.61667,"geocoding":{},"distantMaxMiles":5},"Makanya":{"countryName":"Tanzania","stateName":"Kilimanjaro","name":"Makanya","lat":-4.36667,"lon":37.83333,"geocoding":{},"distantMaxMiles":5},"Moshi":{"countryName":"Tanzania","stateName":"Kilimanjaro","name":"Moshi","lat":-3.35,"lon":37.33333,"geocoding":{},"distantMaxMiles":5},"Mwembe":{"countryName":"Tanzania","stateName":"Kilimanjaro","name":"Mwembe","lat":-4.15,"lon":37.85,"geocoding":{},"distantMaxMiles":5},"Ndungu":{"countryName":"Tanzania","stateName":"Kilimanjaro","name":"Ndungu","lat":-4.36667,"lon":38.05,"geocoding":{},"distantMaxMiles":5},"Same":{"countryName":"Tanzania","stateName":"Kilimanjaro","name":"Same","lat":-4.22199,"lon":37.88278,"geocoding":{},"distantMaxMiles":5}}},"Lindi":{"countryName":"Tanzania","name":"Lindi","isoCode":"12","lat":-9.2343394,"lon":38.3165725,"geocoding":{},"distantMaxMiles":5,"cities":{"Lindi":{"countryName":"Tanzania","stateName":"Lindi","name":"Lindi","lat":-9.99709,"lon":39.71649,"geocoding":{},"distantMaxMiles":5},"Mbekenyera":{"countryName":"Tanzania","stateName":"Lindi","name":"Mbekenyera","lat":-10,"lon":38.98333,"geocoding":{},"distantMaxMiles":5},"Mingoyo":{"countryName":"Tanzania","stateName":"Lindi","name":"Mingoyo","lat":-10.10526,"lon":39.61859,"geocoding":{},"distantMaxMiles":5},"Mtama":{"countryName":"Tanzania","stateName":"Lindi","name":"Mtama","lat":-10.3,"lon":39.36667,"geocoding":{},"distantMaxMiles":5},"Nachingwea":{"countryName":"Tanzania","stateName":"Lindi","name":"Nachingwea","lat":-10.3725,"lon":38.76251,"geocoding":{},"distantMaxMiles":5},"Nyangao":{"countryName":"Tanzania","stateName":"Lindi","name":"Nyangao","lat":-10.33333,"lon":39.28333,"geocoding":{},"distantMaxMiles":5},"Ruangwa":{"countryName":"Tanzania","stateName":"Lindi","name":"Ruangwa","lat":-10.06667,"lon":38.93333,"geocoding":{},"distantMaxMiles":5}}},"Manyara":{"countryName":"Tanzania","name":"Manyara","isoCode":"26","lat":-4.3150058,"lon":36.954107,"geocoding":{},"distantMaxMiles":5,"cities":{"Babati":{"countryName":"Tanzania","stateName":"Manyara","name":"Babati","lat":-4.21667,"lon":35.75,"geocoding":{},"distantMaxMiles":5},"Bashanet":{"countryName":"Tanzania","stateName":"Manyara","name":"Bashanet","lat":-4.23333,"lon":35.41667,"geocoding":{},"distantMaxMiles":5},"Basotu":{"countryName":"Tanzania","stateName":"Manyara","name":"Basotu","lat":-4.36667,"lon":35.08333,"geocoding":{},"distantMaxMiles":5},"Dareda":{"countryName":"Tanzania","stateName":"Manyara","name":"Dareda","lat":-4.21667,"lon":35.55,"geocoding":{},"distantMaxMiles":5},"Dongobesh":{"countryName":"Tanzania","stateName":"Manyara","name":"Dongobesh","lat":-4.06667,"lon":35.38333,"geocoding":{},"distantMaxMiles":5},"Endasak":{"countryName":"Tanzania","stateName":"Manyara","name":"Endasak","lat":-4.41667,"lon":35.51667,"geocoding":{},"distantMaxMiles":5},"Galappo":{"countryName":"Tanzania","stateName":"Manyara","name":"Galappo","lat":-4.26667,"lon":35.85,"geocoding":{},"distantMaxMiles":5},"Katesh":{"countryName":"Tanzania","stateName":"Manyara","name":"Katesh","lat":-4.52483,"lon":35.3849,"geocoding":{},"distantMaxMiles":5},"Kibaya":{"countryName":"Tanzania","stateName":"Manyara","name":"Kibaya","lat":-5.3,"lon":36.56667,"geocoding":{},"distantMaxMiles":5},"Kirya":{"countryName":"Tanzania","stateName":"Manyara","name":"Kirya","lat":-3.91667,"lon":37.48333,"geocoding":{},"distantMaxMiles":5},"Magugu":{"countryName":"Tanzania","stateName":"Manyara","name":"Magugu","lat":-4.01667,"lon":35.76667,"geocoding":{},"distantMaxMiles":5},"Mbulu":{"countryName":"Tanzania","stateName":"Manyara","name":"Mbulu","lat":-3.85,"lon":35.53333,"geocoding":{},"distantMaxMiles":5},"Naberera":{"countryName":"Tanzania","stateName":"Manyara","name":"Naberera","lat":-4.2,"lon":36.93333,"geocoding":{},"distantMaxMiles":5},"Nangwa":{"countryName":"Tanzania","stateName":"Manyara","name":"Nangwa","lat":-4.46667,"lon":35.45,"geocoding":{},"distantMaxMiles":5}}},"Mara":{"countryName":"Tanzania","name":"Mara","isoCode":"13","lat":-1.7753538,"lon":34.1531947,"geocoding":{},"distantMaxMiles":5,"cities":{"Bukonyo":{"countryName":"Tanzania","stateName":"Mara","name":"Bukonyo","lat":-1.95,"lon":32.93333,"geocoding":{},"distantMaxMiles":5},"Butiama":{"countryName":"Tanzania","stateName":"Mara","name":"Butiama","lat":-1.76667,"lon":33.96667,"geocoding":{},"distantMaxMiles":5},"Issenye":{"countryName":"Tanzania","stateName":"Mara","name":"Issenye","lat":-2,"lon":34.33333,"geocoding":{},"distantMaxMiles":5},"Kibara":{"countryName":"Tanzania","stateName":"Mara","name":"Kibara","lat":-2.15,"lon":33.45,"geocoding":{},"distantMaxMiles":5},"Mugango":{"countryName":"Tanzania","stateName":"Mara","name":"Mugango","lat":-1.68333,"lon":33.7,"geocoding":{},"distantMaxMiles":5},"Mugumu":{"countryName":"Tanzania","stateName":"Mara","name":"Mugumu","lat":-1.85,"lon":34.7,"geocoding":{},"distantMaxMiles":5},"Muriti":{"countryName":"Tanzania","stateName":"Mara","name":"Muriti","lat":-1.98333,"lon":32.91667,"geocoding":{},"distantMaxMiles":5},"Musoma":{"countryName":"Tanzania","stateName":"Mara","name":"Musoma","lat":-1.5,"lon":33.8,"geocoding":{},"distantMaxMiles":5},"Nakatunguru":{"countryName":"Tanzania","stateName":"Mara","name":"Nakatunguru","lat":-2.11667,"lon":33.06667,"geocoding":{},"distantMaxMiles":5},"Nansio":{"countryName":"Tanzania","stateName":"Mara","name":"Nansio","lat":-2.13333,"lon":33.05,"geocoding":{},"distantMaxMiles":5},"Nyamuswa":{"countryName":"Tanzania","stateName":"Mara","name":"Nyamuswa","lat":-1.9,"lon":34.01667,"geocoding":{},"distantMaxMiles":5},"Sirari":{"countryName":"Tanzania","stateName":"Mara","name":"Sirari","lat":-1.25367,"lon":34.47596,"geocoding":{},"distantMaxMiles":5}}},"Mbeya":{"countryName":"Tanzania","name":"Mbeya","isoCode":"14","lat":-8.2866112,"lon":32.8132537,"geocoding":{},"distantMaxMiles":5,"cities":{"Chimala":{"countryName":"Tanzania","stateName":"Mbeya","name":"Chimala","lat":-8.85637,"lon":34.02393,"geocoding":{},"distantMaxMiles":5},"Hedaru":{"countryName":"Tanzania","stateName":"Mbeya","name":"Hedaru","lat":-4.5,"lon":37.9,"geocoding":{},"distantMaxMiles":5},"Ibaba":{"countryName":"Tanzania","stateName":"Mbeya","name":"Ibaba","lat":-9.4,"lon":33.35,"geocoding":{},"distantMaxMiles":5},"Ikama":{"countryName":"Tanzania","stateName":"Mbeya","name":"Ikama","lat":-9.26666667,"lon":33.83333333,"geocoding":{},"distantMaxMiles":5},"Ikinga":{"countryName":"Tanzania","stateName":"Mbeya","name":"Ikinga","lat":-9.5,"lon":33.55,"geocoding":{},"distantMaxMiles":5},"Ikolo":{"countryName":"Tanzania","stateName":"Mbeya","name":"Ikolo","lat":-9.65,"lon":33.9,"geocoding":{},"distantMaxMiles":5},"Ikuti":{"countryName":"Tanzania","stateName":"Mbeya","name":"Ikuti","lat":-9.31666667,"lon":33.53333333,"geocoding":{},"distantMaxMiles":5},"Ilembo":{"countryName":"Tanzania","stateName":"Mbeya","name":"Ilembo","lat":-9.25,"lon":33.38333333,"geocoding":{},"distantMaxMiles":5},"Ipinda":{"countryName":"Tanzania","stateName":"Mbeya","name":"Ipinda","lat":-9.48333333,"lon":33.9,"geocoding":{},"distantMaxMiles":5},"Kabula":{"countryName":"Tanzania","stateName":"Mbeya","name":"Kabula","lat":-9.26666667,"lon":33.76666667,"geocoding":{},"distantMaxMiles":5},"Kahe, Tanzania":{"countryName":"Tanzania","stateName":"Mbeya","name":"Kahe, Tanzania","lat":-3.5,"lon":37.433,"geocoding":{},"distantMaxMiles":5},"Kandete":{"countryName":"Tanzania","stateName":"Mbeya","name":"Kandete","lat":-9.15,"lon":33.8,"geocoding":{},"distantMaxMiles":5},"Katumba":{"countryName":"Tanzania","stateName":"Mbeya","name":"Katumba","lat":-9.23333333,"lon":33.61666667,"geocoding":{},"distantMaxMiles":5},"Kihurio":{"countryName":"Tanzania","stateName":"Mbeya","name":"Kihurio","lat":-4.46666667,"lon":38.06666667,"geocoding":{},"distantMaxMiles":5},"Kisiwani":{"countryName":"Tanzania","stateName":"Mbeya","name":"Kisiwani","lat":-4.13333,"lon":37.95,"geocoding":{},"distantMaxMiles":5},"Kiwira":{"countryName":"Tanzania","stateName":"Mbeya","name":"Kiwira","lat":-9.16666667,"lon":33.53333333,"geocoding":{},"distantMaxMiles":5},"Kwakoa":{"countryName":"Tanzania","stateName":"Mbeya","name":"Kwakoa","lat":-3.76666667,"lon":37.71666667,"geocoding":{},"distantMaxMiles":5},"Lembeni":{"countryName":"Tanzania","stateName":"Mbeya","name":"Lembeni","lat":-3.78333333,"lon":37.61666667,"geocoding":{},"distantMaxMiles":5},"Lupata":{"countryName":"Tanzania","stateName":"Mbeya","name":"Lupata","lat":-9.3,"lon":33.85,"geocoding":{},"distantMaxMiles":5},"Lusungo":{"countryName":"Tanzania","stateName":"Mbeya","name":"Lusungo","lat":-9.5,"lon":33.98333333,"geocoding":{},"distantMaxMiles":5},"Machame":{"countryName":"Tanzania","stateName":"Mbeya","name":"Machame","lat":-3.20611111,"lon":37.22638889,"geocoding":{},"distantMaxMiles":5},"Makanya":{"countryName":"Tanzania","stateName":"Mbeya","name":"Makanya","lat":-4.36666667,"lon":37.83333333,"geocoding":{},"distantMaxMiles":5},"Marangu":{"countryName":"Tanzania","stateName":"Mbeya","name":"Marangu","lat":-3.28333,"lon":37.51667,"geocoding":{},"distantMaxMiles":5},"Masukulu":{"countryName":"Tanzania","stateName":"Mbeya","name":"Masukulu","lat":-9.4,"lon":33.75,"geocoding":{},"distantMaxMiles":5},"Mbeya":{"countryName":"Tanzania","stateName":"Mbeya","name":"Mbeya","lat":-8.9,"lon":33.45,"geocoding":{},"distantMaxMiles":5},"Mlowo":{"countryName":"Tanzania","stateName":"Mbeya","name":"Mlowo","lat":-9,"lon":32.98333333,"geocoding":{},"distantMaxMiles":5},"Moshi":{"countryName":"Tanzania","stateName":"Mbeya","name":"Moshi","lat":-3.33488333,"lon":37.34038056,"geocoding":{},"distantMaxMiles":5},"Mpuguso":{"countryName":"Tanzania","stateName":"Mbeya","name":"Mpuguso","lat":-9.31666667,"lon":33.65,"geocoding":{},"distantMaxMiles":5},"Mwansanga":{"countryName":"Tanzania","stateName":"Mbeya","name":"Mwansanga","lat":-8.76666667,"lon":33.53333333,"geocoding":{},"distantMaxMiles":5},"Mwaya":{"countryName":"Tanzania","stateName":"Mbeya","name":"Mwaya","lat":-9.55,"lon":33.95,"geocoding":{},"distantMaxMiles":5},"Mwembe":{"countryName":"Tanzania","stateName":"Mbeya","name":"Mwembe","lat":-4.15,"lon":37.85,"geocoding":{},"distantMaxMiles":5},"Same":{"countryName":"Tanzania","stateName":"Mbeya","name":"Same","lat":-4.06666667,"lon":37.78333333,"geocoding":{},"distantMaxMiles":5},"Tukuyu":{"countryName":"Tanzania","stateName":"Mbeya","name":"Tukuyu","lat":-9.25833333,"lon":33.64166667,"geocoding":{},"distantMaxMiles":5},"Tunduma":{"countryName":"Tanzania","stateName":"Mbeya","name":"Tunduma","lat":-9.3,"lon":32.7667,"geocoding":{},"distantMaxMiles":5},"Ugweno":{"countryName":"Tanzania","stateName":"Mbeya","name":"Ugweno","lat":-3.65,"lon":37.65,"geocoding":{},"distantMaxMiles":5},"Ulanga":{"countryName":"Tanzania","stateName":"Mbeya","name":"Ulanga","lat":-8.34361,"lon":34.2897,"geocoding":{},"distantMaxMiles":5}}},"Morogoro":{"countryName":"Tanzania","name":"Morogoro","isoCode":"16","lat":-8.8137173,"lon":36.954107,"geocoding":{},"distantMaxMiles":5,"cities":{"Geiro":{"countryName":"Tanzania","stateName":"Morogoro","name":"Geiro","lat":-6.15,"lon":36.86667,"geocoding":{},"distantMaxMiles":5},"Ifakara":{"countryName":"Tanzania","stateName":"Morogoro","name":"Ifakara","lat":-8.13333,"lon":36.68333,"geocoding":{},"distantMaxMiles":5},"Kidatu":{"countryName":"Tanzania","stateName":"Morogoro","name":"Kidatu","lat":-7.69916,"lon":36.95722,"geocoding":{},"distantMaxMiles":5},"Kidodi":{"countryName":"Tanzania","stateName":"Morogoro","name":"Kidodi","lat":-7.60361,"lon":37.00438,"geocoding":{},"distantMaxMiles":5},"Kilosa":{"countryName":"Tanzania","stateName":"Morogoro","name":"Kilosa","lat":-6.83333,"lon":36.98333,"geocoding":{},"distantMaxMiles":5},"Kimamba":{"countryName":"Tanzania","stateName":"Morogoro","name":"Kimamba","lat":-6.78333,"lon":37.13333,"geocoding":{},"distantMaxMiles":5},"Kisanga":{"countryName":"Tanzania","stateName":"Morogoro","name":"Kisanga","lat":-7.43622,"lon":37.70337,"geocoding":{},"distantMaxMiles":5},"Lupiro":{"countryName":"Tanzania","stateName":"Morogoro","name":"Lupiro","lat":-8.38333,"lon":36.66667,"geocoding":{},"distantMaxMiles":5},"Magole":{"countryName":"Tanzania","stateName":"Morogoro","name":"Magole","lat":-6.37697,"lon":37.37373,"geocoding":{},"distantMaxMiles":5},"Mahenge":{"countryName":"Tanzania","stateName":"Morogoro","name":"Mahenge","lat":-8.68333,"lon":36.71667,"geocoding":{},"distantMaxMiles":5},"Malinyi":{"countryName":"Tanzania","stateName":"Morogoro","name":"Malinyi","lat":-8.93333,"lon":36.13333,"geocoding":{},"distantMaxMiles":5},"Mikumi":{"countryName":"Tanzania","stateName":"Morogoro","name":"Mikumi","lat":-7.40409,"lon":36.98309,"geocoding":{},"distantMaxMiles":5},"Mlimba":{"countryName":"Tanzania","stateName":"Morogoro","name":"Mlimba","lat":-8.8,"lon":35.81667,"geocoding":{},"distantMaxMiles":5},"Morogoro":{"countryName":"Tanzania","stateName":"Morogoro","name":"Morogoro","lat":-6.82102,"lon":37.66122,"geocoding":{},"distantMaxMiles":5},"Msowero":{"countryName":"Tanzania","stateName":"Morogoro","name":"Msowero","lat":-6.53333,"lon":37.2,"geocoding":{},"distantMaxMiles":5},"Mtimbira":{"countryName":"Tanzania","stateName":"Morogoro","name":"Mtimbira","lat":-8.78333,"lon":36.35,"geocoding":{},"distantMaxMiles":5},"Mvomero District":{"countryName":"Tanzania","stateName":"Morogoro","name":"Mvomero District","lat":-6.3,"lon":37.45,"geocoding":{},"distantMaxMiles":5},"Ngerengere":{"countryName":"Tanzania","stateName":"Morogoro","name":"Ngerengere","lat":-6.75,"lon":38.11667,"geocoding":{},"distantMaxMiles":5}}},"Mtwara":{"countryName":"Tanzania","name":"Mtwara","isoCode":"17","lat":-10.3398455,"lon":40.1657466,"geocoding":{},"distantMaxMiles":5,"cities":{"Chiungutwa":{"countryName":"Tanzania","stateName":"Mtwara","name":"Chiungutwa","lat":-10.88333,"lon":38.98333,"geocoding":{},"distantMaxMiles":5},"Kitama":{"countryName":"Tanzania","stateName":"Mtwara","name":"Kitama","lat":-10.71667,"lon":39.73333,"geocoding":{},"distantMaxMiles":5},"Kitangari":{"countryName":"Tanzania","stateName":"Mtwara","name":"Kitangari","lat":-10.65,"lon":39.33333,"geocoding":{},"distantMaxMiles":5},"Luchingu":{"countryName":"Tanzania","stateName":"Mtwara","name":"Luchingu","lat":-10.9,"lon":39.33333,"geocoding":{},"distantMaxMiles":5},"Lukuledi":{"countryName":"Tanzania","stateName":"Mtwara","name":"Lukuledi","lat":-10.56667,"lon":38.8,"geocoding":{},"distantMaxMiles":5},"Lulindi":{"countryName":"Tanzania","stateName":"Mtwara","name":"Lulindi","lat":-10.81667,"lon":39.13333,"geocoding":{},"distantMaxMiles":5},"Madimba":{"countryName":"Tanzania","stateName":"Mtwara","name":"Madimba","lat":-10.4,"lon":40.33333,"geocoding":{},"distantMaxMiles":5},"Mahuta":{"countryName":"Tanzania","stateName":"Mtwara","name":"Mahuta","lat":-10.86667,"lon":39.45,"geocoding":{},"distantMaxMiles":5},"Masasi":{"countryName":"Tanzania","stateName":"Mtwara","name":"Masasi","lat":-10.71667,"lon":38.8,"geocoding":{},"distantMaxMiles":5},"Masuguru":{"countryName":"Tanzania","stateName":"Mtwara","name":"Masuguru","lat":-11.36667,"lon":38.41667,"geocoding":{},"distantMaxMiles":5},"Mtwara":{"countryName":"Tanzania","stateName":"Mtwara","name":"Mtwara","lat":-10.26667,"lon":40.18333,"geocoding":{},"distantMaxMiles":5},"Namalenga":{"countryName":"Tanzania","stateName":"Mtwara","name":"Namalenga","lat":-10.95,"lon":39.1,"geocoding":{},"distantMaxMiles":5},"Namikupa":{"countryName":"Tanzania","stateName":"Mtwara","name":"Namikupa","lat":-10.83333,"lon":39.6,"geocoding":{},"distantMaxMiles":5},"Nanganga":{"countryName":"Tanzania","stateName":"Mtwara","name":"Nanganga","lat":-10.38333,"lon":39.15,"geocoding":{},"distantMaxMiles":5},"Nangomba":{"countryName":"Tanzania","stateName":"Mtwara","name":"Nangomba","lat":-10.9,"lon":38.5,"geocoding":{},"distantMaxMiles":5},"Nanhyanga":{"countryName":"Tanzania","stateName":"Mtwara","name":"Nanhyanga","lat":-10.8,"lon":39.55,"geocoding":{},"distantMaxMiles":5},"Nanyamba":{"countryName":"Tanzania","stateName":"Mtwara","name":"Nanyamba","lat":-10.68333,"lon":39.83333,"geocoding":{},"distantMaxMiles":5},"Newala Kisimani":{"countryName":"Tanzania","stateName":"Mtwara","name":"Newala Kisimani","lat":-10.95,"lon":39.28333,"geocoding":{},"distantMaxMiles":5},"Tandahimba":{"countryName":"Tanzania","stateName":"Mtwara","name":"Tandahimba","lat":-10.75,"lon":39.63333,"geocoding":{},"distantMaxMiles":5}}},"Mwanza":{"countryName":"Tanzania","name":"Mwanza","isoCode":"18","lat":-2.4671197,"lon":32.8986812,"geocoding":{},"distantMaxMiles":5,"cities":{"Ilemela District":{"countryName":"Tanzania","stateName":"Mwanza","name":"Ilemela District","lat":-2.44783,"lon":33.03177,"geocoding":{},"distantMaxMiles":5},"Kihangara":{"countryName":"Tanzania","stateName":"Mwanza","name":"Kihangara","lat":-2.58333,"lon":33.35,"geocoding":{},"distantMaxMiles":5},"Malya":{"countryName":"Tanzania","stateName":"Mwanza","name":"Malya","lat":-2.98333,"lon":33.51667,"geocoding":{},"distantMaxMiles":5},"Misasi":{"countryName":"Tanzania","stateName":"Mwanza","name":"Misasi","lat":-3,"lon":33.08333,"geocoding":{},"distantMaxMiles":5},"Misungwi":{"countryName":"Tanzania","stateName":"Mwanza","name":"Misungwi","lat":-2.85,"lon":33.08333,"geocoding":{},"distantMaxMiles":5},"Mwanza":{"countryName":"Tanzania","stateName":"Mwanza","name":"Mwanza","lat":-2.51667,"lon":32.9,"geocoding":{},"distantMaxMiles":5},"Ngudu":{"countryName":"Tanzania","stateName":"Mwanza","name":"Ngudu","lat":-2.96667,"lon":33.33333,"geocoding":{},"distantMaxMiles":5},"Nyanguge":{"countryName":"Tanzania","stateName":"Mwanza","name":"Nyanguge","lat":-2.55,"lon":33.2,"geocoding":{},"distantMaxMiles":5},"Usagara":{"countryName":"Tanzania","stateName":"Mwanza","name":"Usagara","lat":-2.68333,"lon":33,"geocoding":{},"distantMaxMiles":5}}},"Njombe":{"countryName":"Tanzania","name":"Njombe","isoCode":"29","lat":-9.2422632,"lon":35.1268781,"geocoding":{},"distantMaxMiles":5,"cities":{"Ilembula":{"countryName":"Tanzania","stateName":"Njombe","name":"Ilembula","lat":-8.9,"lon":34.58333,"geocoding":{},"distantMaxMiles":5},"Makumbako":{"countryName":"Tanzania","stateName":"Njombe","name":"Makumbako","lat":-8.85,"lon":34.83333,"geocoding":{},"distantMaxMiles":5},"Manda":{"countryName":"Tanzania","stateName":"Njombe","name":"Manda","lat":-10.46667,"lon":34.58333,"geocoding":{},"distantMaxMiles":5},"Matamba":{"countryName":"Tanzania","stateName":"Njombe","name":"Matamba","lat":-8.98333,"lon":33.96667,"geocoding":{},"distantMaxMiles":5},"Mlangali":{"countryName":"Tanzania","stateName":"Njombe","name":"Mlangali","lat":-9.78333,"lon":34.51667,"geocoding":{},"distantMaxMiles":5},"Mtwango":{"countryName":"Tanzania","stateName":"Njombe","name":"Mtwango","lat":-9.01667,"lon":34.8,"geocoding":{},"distantMaxMiles":5},"Njombe":{"countryName":"Tanzania","stateName":"Njombe","name":"Njombe","lat":-9.34917,"lon":34.77167,"geocoding":{},"distantMaxMiles":5}}},"Pemba North":{"countryName":"Tanzania","name":"Pemba North","isoCode":"06","lat":-5.0319352,"lon":39.7755571,"geocoding":{},"distantMaxMiles":5,"cities":{"Konde":{"countryName":"Tanzania","stateName":"Pemba North","name":"Konde","lat":-4.95,"lon":39.75,"geocoding":{},"distantMaxMiles":5},"Micheweni":{"countryName":"Tanzania","stateName":"Pemba North","name":"Micheweni","lat":-4.96667,"lon":39.83333,"geocoding":{},"distantMaxMiles":5},"Wete":{"countryName":"Tanzania","stateName":"Pemba North","name":"Wete","lat":-5.05589,"lon":39.72938,"geocoding":{},"distantMaxMiles":5}}},"Pemba South":{"countryName":"Tanzania","name":"Pemba South","isoCode":"10","lat":-5.3146961,"lon":39.7549511,"geocoding":{},"distantMaxMiles":5,"cities":{"Chake Chake":{"countryName":"Tanzania","stateName":"Pemba South","name":"Chake Chake","lat":-5.24586,"lon":39.76659,"geocoding":{},"distantMaxMiles":5},"Mtambile":{"countryName":"Tanzania","stateName":"Pemba South","name":"Mtambile","lat":-5.38333,"lon":39.7,"geocoding":{},"distantMaxMiles":5},"Uwelini":{"countryName":"Tanzania","stateName":"Pemba South","name":"Uwelini","lat":-5.4,"lon":39.68333,"geocoding":{},"distantMaxMiles":5}}},"Pwani":{"countryName":"Tanzania","name":"Pwani","isoCode":"19","lat":-7.3237714,"lon":38.8205454,"geocoding":{},"distantMaxMiles":5,"cities":{"Bagamoyo":{"countryName":"Tanzania","stateName":"Pwani","name":"Bagamoyo","lat":-6.44222,"lon":38.90422,"geocoding":{},"distantMaxMiles":5},"Bungu":{"countryName":"Tanzania","stateName":"Pwani","name":"Bungu","lat":-7.63369,"lon":39.05818,"geocoding":{},"distantMaxMiles":5},"Chalinze":{"countryName":"Tanzania","stateName":"Pwani","name":"Chalinze","lat":-6.63784,"lon":38.35396,"geocoding":{},"distantMaxMiles":5},"Ikwiriri":{"countryName":"Tanzania","stateName":"Pwani","name":"Ikwiriri","lat":-7.95618,"lon":38.97164,"geocoding":{},"distantMaxMiles":5},"Kibaha":{"countryName":"Tanzania","stateName":"Pwani","name":"Kibaha","lat":-6.76667,"lon":38.91667,"geocoding":{},"distantMaxMiles":5},"Kibiti":{"countryName":"Tanzania","stateName":"Pwani","name":"Kibiti","lat":-7.72178,"lon":38.93749,"geocoding":{},"distantMaxMiles":5},"Kilindoni":{"countryName":"Tanzania","stateName":"Pwani","name":"Kilindoni","lat":-7.91446,"lon":39.66204,"geocoding":{},"distantMaxMiles":5},"Kisarawe":{"countryName":"Tanzania","stateName":"Pwani","name":"Kisarawe","lat":-6.9,"lon":39.06667,"geocoding":{},"distantMaxMiles":5},"Lugoba":{"countryName":"Tanzania","stateName":"Pwani","name":"Lugoba","lat":-6.45,"lon":38.33333,"geocoding":{},"distantMaxMiles":5},"Maneromango":{"countryName":"Tanzania","stateName":"Pwani","name":"Maneromango","lat":-7.1988,"lon":38.78478,"geocoding":{},"distantMaxMiles":5},"Mbumi":{"countryName":"Tanzania","stateName":"Pwani","name":"Mbumi","lat":-7.90577,"lon":39.21047,"geocoding":{},"distantMaxMiles":5},"Mkuranga":{"countryName":"Tanzania","stateName":"Pwani","name":"Mkuranga","lat":-7.27,"lon":39.2,"geocoding":{},"distantMaxMiles":5},"Mlandizi":{"countryName":"Tanzania","stateName":"Pwani","name":"Mlandizi","lat":-6.7,"lon":38.73333,"geocoding":{},"distantMaxMiles":5},"Mvomero":{"countryName":"Tanzania","stateName":"Pwani","name":"Mvomero","lat":-6.25,"lon":38.66667,"geocoding":{},"distantMaxMiles":5},"Utete":{"countryName":"Tanzania","stateName":"Pwani","name":"Utete","lat":-7.98598,"lon":38.75795,"geocoding":{},"distantMaxMiles":5},"Vikindu":{"countryName":"Tanzania","stateName":"Pwani","name":"Vikindu","lat":-7.00667,"lon":39.29849,"geocoding":{},"distantMaxMiles":5}}},"Rukwa":{"countryName":"Tanzania","name":"Rukwa","isoCode":"20","lat":-8.0109444,"lon":31.4456179,"geocoding":{},"distantMaxMiles":5,"cities":{"Chala":{"countryName":"Tanzania","stateName":"Rukwa","name":"Chala","lat":-7.58333,"lon":31.26667,"geocoding":{},"distantMaxMiles":5},"Kirando":{"countryName":"Tanzania","stateName":"Rukwa","name":"Kirando","lat":-7.41667,"lon":30.6,"geocoding":{},"distantMaxMiles":5},"Laela":{"countryName":"Tanzania","stateName":"Rukwa","name":"Laela","lat":-8.56667,"lon":32.05,"geocoding":{},"distantMaxMiles":5},"Matai":{"countryName":"Tanzania","stateName":"Rukwa","name":"Matai","lat":-8.3,"lon":31.51667,"geocoding":{},"distantMaxMiles":5},"Namanyere":{"countryName":"Tanzania","stateName":"Rukwa","name":"Namanyere","lat":-7.51667,"lon":31.05,"geocoding":{},"distantMaxMiles":5},"Nkove":{"countryName":"Tanzania","stateName":"Rukwa","name":"Nkove","lat":-7.95,"lon":30.85,"geocoding":{},"distantMaxMiles":5},"Sumbawanga":{"countryName":"Tanzania","stateName":"Rukwa","name":"Sumbawanga","lat":-7.96667,"lon":31.61667,"geocoding":{},"distantMaxMiles":5}}},"Ruvuma":{"countryName":"Tanzania","name":"Ruvuma","isoCode":"21","lat":-10.6878717,"lon":36.2630846,"geocoding":{},"distantMaxMiles":5,"cities":{"Kigonsera":{"countryName":"Tanzania","stateName":"Ruvuma","name":"Kigonsera","lat":-10.8,"lon":35.05,"geocoding":{},"distantMaxMiles":5},"Liuli":{"countryName":"Tanzania","stateName":"Ruvuma","name":"Liuli","lat":-11.08333,"lon":34.63333,"geocoding":{},"distantMaxMiles":5},"Mahanje":{"countryName":"Tanzania","stateName":"Ruvuma","name":"Mahanje","lat":-9.93333,"lon":35.33333,"geocoding":{},"distantMaxMiles":5},"Maposeni":{"countryName":"Tanzania","stateName":"Ruvuma","name":"Maposeni","lat":-10.58333,"lon":35.4,"geocoding":{},"distantMaxMiles":5},"Matiri":{"countryName":"Tanzania","stateName":"Ruvuma","name":"Matiri","lat":-10.75,"lon":34.9,"geocoding":{},"distantMaxMiles":5},"Mbamba Bay":{"countryName":"Tanzania","stateName":"Ruvuma","name":"Mbamba Bay","lat":-11.28333,"lon":34.76667,"geocoding":{},"distantMaxMiles":5},"Mbinga":{"countryName":"Tanzania","stateName":"Ruvuma","name":"Mbinga","lat":-10.93333,"lon":35.01667,"geocoding":{},"distantMaxMiles":5},"Songea":{"countryName":"Tanzania","stateName":"Ruvuma","name":"Songea","lat":-10.68333,"lon":35.65,"geocoding":{},"distantMaxMiles":5},"Tingi":{"countryName":"Tanzania","stateName":"Ruvuma","name":"Tingi","lat":-11.3,"lon":35.03333,"geocoding":{},"distantMaxMiles":5}}},"Shinyanga":{"countryName":"Tanzania","name":"Shinyanga","isoCode":"22","lat":-3.6809961,"lon":33.4271403,"geocoding":{},"distantMaxMiles":5,"cities":{"Isaka":{"countryName":"Tanzania","stateName":"Shinyanga","name":"Isaka","lat":-3.9,"lon":32.93333,"geocoding":{},"distantMaxMiles":5},"Kahama":{"countryName":"Tanzania","stateName":"Shinyanga","name":"Kahama","lat":-3.83333,"lon":32.6,"geocoding":{},"distantMaxMiles":5},"Kishapu":{"countryName":"Tanzania","stateName":"Shinyanga","name":"Kishapu","lat":-3.61667,"lon":33.86667,"geocoding":{},"distantMaxMiles":5},"Mhango":{"countryName":"Tanzania","stateName":"Shinyanga","name":"Mhango","lat":-3.28333,"lon":32.85,"geocoding":{},"distantMaxMiles":5},"Mwadui":{"countryName":"Tanzania","stateName":"Shinyanga","name":"Mwadui","lat":-3.55,"lon":33.6,"geocoding":{},"distantMaxMiles":5},"Old Shinyanga":{"countryName":"Tanzania","stateName":"Shinyanga","name":"Old Shinyanga","lat":-3.55,"lon":33.4,"geocoding":{},"distantMaxMiles":5},"Shinyanga":{"countryName":"Tanzania","stateName":"Shinyanga","name":"Shinyanga","lat":-3.66393,"lon":33.42118,"geocoding":{},"distantMaxMiles":5},"Songwa":{"countryName":"Tanzania","stateName":"Shinyanga","name":"Songwa","lat":-3.51667,"lon":33.51667,"geocoding":{},"distantMaxMiles":5},"Tinde":{"countryName":"Tanzania","stateName":"Shinyanga","name":"Tinde","lat":-3.88333,"lon":33.2,"geocoding":{},"distantMaxMiles":5}}},"Simiyu":{"countryName":"Tanzania","name":"Simiyu","isoCode":"30","lat":-2.8308738,"lon":34.1531947,"geocoding":{},"distantMaxMiles":5,"cities":{"Bariadi":{"countryName":"Tanzania","stateName":"Simiyu","name":"Bariadi","lat":-2.8,"lon":33.98333,"geocoding":{},"distantMaxMiles":5},"Kisesa":{"countryName":"Tanzania","stateName":"Simiyu","name":"Kisesa","lat":-3.08333,"lon":34.15,"geocoding":{},"distantMaxMiles":5},"Lalago":{"countryName":"Tanzania","stateName":"Simiyu","name":"Lalago","lat":-3.45,"lon":33.95,"geocoding":{},"distantMaxMiles":5},"Malampaka":{"countryName":"Tanzania","stateName":"Simiyu","name":"Malampaka","lat":-3.13333,"lon":33.53333,"geocoding":{},"distantMaxMiles":5},"Maswa":{"countryName":"Tanzania","stateName":"Simiyu","name":"Maswa","lat":-2.68333,"lon":33.98333,"geocoding":{},"distantMaxMiles":5},"Matonga":{"countryName":"Tanzania","stateName":"Simiyu","name":"Matonga","lat":-2.38333,"lon":34.08333,"geocoding":{},"distantMaxMiles":5},"Nyakabindi":{"countryName":"Tanzania","stateName":"Simiyu","name":"Nyakabindi","lat":-2.63333,"lon":33.98333,"geocoding":{},"distantMaxMiles":5},"Nyalikungu":{"countryName":"Tanzania","stateName":"Simiyu","name":"Nyalikungu","lat":-3.18333,"lon":33.78333,"geocoding":{},"distantMaxMiles":5},"Somanda":{"countryName":"Tanzania","stateName":"Simiyu","name":"Somanda","lat":-3.36667,"lon":33.95,"geocoding":{},"distantMaxMiles":5}}},"Singida":{"countryName":"Tanzania","name":"Singida","isoCode":"23","lat":-6.7453352,"lon":34.1531947,"geocoding":{},"distantMaxMiles":5,"cities":{"Igugunu":{"countryName":"Tanzania","stateName":"Singida","name":"Igugunu","lat":-4.56667,"lon":34.63333,"geocoding":{},"distantMaxMiles":5},"Ikungi":{"countryName":"Tanzania","stateName":"Singida","name":"Ikungi","lat":-5.13333,"lon":34.76667,"geocoding":{},"distantMaxMiles":5},"Ilongero":{"countryName":"Tanzania","stateName":"Singida","name":"Ilongero","lat":-4.66667,"lon":34.86667,"geocoding":{},"distantMaxMiles":5},"Itigi":{"countryName":"Tanzania","stateName":"Singida","name":"Itigi","lat":-5.7,"lon":34.48333,"geocoding":{},"distantMaxMiles":5},"Kilimatinde":{"countryName":"Tanzania","stateName":"Singida","name":"Kilimatinde","lat":-5.85,"lon":34.95,"geocoding":{},"distantMaxMiles":5},"Kintinku":{"countryName":"Tanzania","stateName":"Singida","name":"Kintinku","lat":-5.88333,"lon":35.23333,"geocoding":{},"distantMaxMiles":5},"Kiomboi":{"countryName":"Tanzania","stateName":"Singida","name":"Kiomboi","lat":-4.26667,"lon":34.36667,"geocoding":{},"distantMaxMiles":5},"Mgandu":{"countryName":"Tanzania","stateName":"Singida","name":"Mgandu","lat":-5.95,"lon":34.13333,"geocoding":{},"distantMaxMiles":5},"Mtinko":{"countryName":"Tanzania","stateName":"Singida","name":"Mtinko","lat":-4.55,"lon":34.85,"geocoding":{},"distantMaxMiles":5},"Mungaa":{"countryName":"Tanzania","stateName":"Singida","name":"Mungaa","lat":-4.96667,"lon":34.88333,"geocoding":{},"distantMaxMiles":5},"Ndago":{"countryName":"Tanzania","stateName":"Singida","name":"Ndago","lat":-4.6,"lon":34.35,"geocoding":{},"distantMaxMiles":5},"Puma":{"countryName":"Tanzania","stateName":"Singida","name":"Puma","lat":-5,"lon":34.73333,"geocoding":{},"distantMaxMiles":5},"Sepuka":{"countryName":"Tanzania","stateName":"Singida","name":"Sepuka","lat":-4.75,"lon":34.53333,"geocoding":{},"distantMaxMiles":5},"Shelui":{"countryName":"Tanzania","stateName":"Singida","name":"Shelui","lat":-4.36667,"lon":34.2,"geocoding":{},"distantMaxMiles":5},"Singida":{"countryName":"Tanzania","stateName":"Singida","name":"Singida","lat":-4.81629,"lon":34.74358,"geocoding":{},"distantMaxMiles":5}}},"Songwe":{"countryName":"Tanzania","name":"Songwe","isoCode":"31","lat":-8.272612,"lon":31.7113174,"geocoding":{},"distantMaxMiles":5,"cities":{}},"Tabora":{"countryName":"Tanzania","name":"Tabora","isoCode":"24","lat":-5.0342138,"lon":32.8084496,"geocoding":{},"distantMaxMiles":5,"cities":{"Bukene":{"countryName":"Tanzania","stateName":"Tabora","name":"Bukene","lat":-4.23333,"lon":32.88333,"geocoding":{},"distantMaxMiles":5},"Igurubi":{"countryName":"Tanzania","stateName":"Tabora","name":"Igurubi","lat":-4,"lon":33.7,"geocoding":{},"distantMaxMiles":5},"Kaliua":{"countryName":"Tanzania","stateName":"Tabora","name":"Kaliua","lat":-5.06056,"lon":31.79361,"geocoding":{},"distantMaxMiles":5},"Mabama":{"countryName":"Tanzania","stateName":"Tabora","name":"Mabama","lat":-5.13333,"lon":32.53333,"geocoding":{},"distantMaxMiles":5},"Sikonge":{"countryName":"Tanzania","stateName":"Tabora","name":"Sikonge","lat":-5.63333,"lon":32.76667,"geocoding":{},"distantMaxMiles":5},"Tabora":{"countryName":"Tanzania","stateName":"Tabora","name":"Tabora","lat":-5.01622,"lon":32.82663,"geocoding":{},"distantMaxMiles":5},"Tumbi":{"countryName":"Tanzania","stateName":"Tabora","name":"Tumbi","lat":-5.06667,"lon":32.73333,"geocoding":{},"distantMaxMiles":5},"Usoke":{"countryName":"Tanzania","stateName":"Tabora","name":"Usoke","lat":-5.16667,"lon":32.35,"geocoding":{},"distantMaxMiles":5}}},"Tanga":{"countryName":"Tanzania","name":"Tanga","isoCode":"25","lat":-5.3049789,"lon":38.3165725,"geocoding":{},"distantMaxMiles":5,"cities":{"Chanika":{"countryName":"Tanzania","stateName":"Tanga","name":"Chanika","lat":-5.41667,"lon":38.01667,"geocoding":{},"distantMaxMiles":5},"Lushoto":{"countryName":"Tanzania","stateName":"Tanga","name":"Lushoto","lat":-4.78333,"lon":38.28333,"geocoding":{},"distantMaxMiles":5},"Magomeni":{"countryName":"Tanzania","stateName":"Tanga","name":"Magomeni","lat":-5.23333,"lon":38.11667,"geocoding":{},"distantMaxMiles":5},"Majengo":{"countryName":"Tanzania","stateName":"Tanga","name":"Majengo","lat":-5.15,"lon":38.98333,"geocoding":{},"distantMaxMiles":5},"Makuyuni":{"countryName":"Tanzania","stateName":"Tanga","name":"Makuyuni","lat":-4.73333,"lon":38.1,"geocoding":{},"distantMaxMiles":5},"Maramba":{"countryName":"Tanzania","stateName":"Tanga","name":"Maramba","lat":-5.05,"lon":38.61667,"geocoding":{},"distantMaxMiles":5},"Matui":{"countryName":"Tanzania","stateName":"Tanga","name":"Matui","lat":-4.8,"lon":38.25,"geocoding":{},"distantMaxMiles":5},"Mazinde":{"countryName":"Tanzania","stateName":"Tanga","name":"Mazinde","lat":-4.8,"lon":38.21667,"geocoding":{},"distantMaxMiles":5},"Mlalo":{"countryName":"Tanzania","stateName":"Tanga","name":"Mlalo","lat":-4.93333,"lon":38.93333,"geocoding":{},"distantMaxMiles":5},"Muheza":{"countryName":"Tanzania","stateName":"Tanga","name":"Muheza","lat":-5.16667,"lon":38.78333,"geocoding":{},"distantMaxMiles":5},"Mwanga":{"countryName":"Tanzania","stateName":"Tanga","name":"Mwanga","lat":-4.8,"lon":38.2,"geocoding":{},"distantMaxMiles":5},"Pangani":{"countryName":"Tanzania","stateName":"Tanga","name":"Pangani","lat":-5.42526,"lon":38.97473,"geocoding":{},"distantMaxMiles":5},"Soni":{"countryName":"Tanzania","stateName":"Tanga","name":"Soni","lat":-4.85,"lon":38.36667,"geocoding":{},"distantMaxMiles":5},"Tanga":{"countryName":"Tanzania","stateName":"Tanga","name":"Tanga","lat":-5.06893,"lon":39.09875,"geocoding":{},"distantMaxMiles":5}}},"Zanzibar North":{"countryName":"Tanzania","name":"Zanzibar North","isoCode":"07","lat":-5.9395093,"lon":39.2791011,"geocoding":{},"distantMaxMiles":5,"cities":{"Gamba":{"countryName":"Tanzania","stateName":"Zanzibar North","name":"Gamba","lat":-5.9,"lon":39.3,"geocoding":{},"distantMaxMiles":5},"Kijini":{"countryName":"Tanzania","stateName":"Zanzibar North","name":"Kijini","lat":-5.85,"lon":39.31667,"geocoding":{},"distantMaxMiles":5},"Kiwengwa":{"countryName":"Tanzania","stateName":"Zanzibar North","name":"Kiwengwa","lat":-5.98957,"lon":39.3768,"geocoding":{},"distantMaxMiles":5},"Mkokotoni":{"countryName":"Tanzania","stateName":"Zanzibar North","name":"Mkokotoni","lat":-5.87506,"lon":39.25523,"geocoding":{},"distantMaxMiles":5},"Nungwi":{"countryName":"Tanzania","stateName":"Zanzibar North","name":"Nungwi","lat":-5.72651,"lon":39.2987,"geocoding":{},"distantMaxMiles":5}}},"Zanzibar South":{"countryName":"Tanzania","name":"Zanzibar South","isoCode":"11","lat":-6.2642851,"lon":39.4450281,"geocoding":{},"distantMaxMiles":5,"cities":{"Koani":{"countryName":"Tanzania","stateName":"Zanzibar South","name":"Koani","lat":-6.13333,"lon":39.28333,"geocoding":{},"distantMaxMiles":5},"Koani Ndogo":{"countryName":"Tanzania","stateName":"Zanzibar South","name":"Koani Ndogo","lat":-6.13333,"lon":39.28333,"geocoding":{},"distantMaxMiles":5},"Mahonda":{"countryName":"Tanzania","stateName":"Zanzibar South","name":"Mahonda","lat":-6.45,"lon":39.46667,"geocoding":{},"distantMaxMiles":5},"Nganane":{"countryName":"Tanzania","stateName":"Zanzibar South","name":"Nganane","lat":-6.4,"lon":39.55,"geocoding":{},"distantMaxMiles":5},"Sokoni":{"countryName":"Tanzania","stateName":"Zanzibar South","name":"Sokoni","lat":-6.43333,"lon":39.55,"geocoding":{},"distantMaxMiles":5}}},"Zanzibar West":{"countryName":"Tanzania","name":"Zanzibar West","isoCode":"15","lat":-6.2298136,"lon":39.2583293,"geocoding":{},"distantMaxMiles":5,"cities":{"Zanzibar":{"countryName":"Tanzania","stateName":"Zanzibar West","name":"Zanzibar","lat":-6.16394,"lon":39.19793,"geocoding":{},"distantMaxMiles":5}}}}}